xts/__init__.py
xts-0.0.15.dist-info/METADATA
xts-0.0.15.dist-info/WHEEL
xts-0.0.15.dist-info/top_level.txt
xts-0.0.15.dist-info/RECORD
