Metadata-Version: 2.4
Name: xts
Version: 0.0.15
Summary: xts is the Python SDK for XT Systems
Author-email: Josh XT <josh@devxt.com>
Project-URL: Homepage, https://github.com/DevXT-LLC/xts
Project-URL: Repository, https://github.com/DevXT-LLC/xts
Keywords: xts,xt-systems,sdk
Classifier: Development Status :: 3 - Alpha
Classifier: Intended Audience :: Developers
Classifier: License :: OSI Approved :: MIT License
Classifier: Programming Language :: Python :: 3
Classifier: Programming Language :: Python :: 3.10
Classifier: Programming Language :: Python :: 3.11
Classifier: Programming Language :: Python :: 3.12
Requires-Python: >=3.10
Requires-Dist: requests
Requires-Dist: pyotp
